internal_dateutil/__init__.py
internal_dateutil-0.0.1.dist-info/METADATA
internal_dateutil-0.0.1.dist-info/WHEEL
internal_dateutil-0.0.1.dist-info/top_level.txt
internal_dateutil-0.0.1.dist-info/RECORD
