Metadata-Version: 2.1
Name: internal-dateutil
Version: 0.0.1
Summary: Dependency Confusion PoC
Author: sl4x0
Author-email: sl4x0@example.com
